craigslist.py
craigslist_rental_market-0.1.0.dist-info/DESCRIPTION.rst
craigslist_rental_market-0.1.0.dist-info/METADATA
craigslist_rental_market-0.1.0.dist-info/RECORD
craigslist_rental_market-0.1.0.dist-info/WHEEL
craigslist_rental_market-0.1.0.dist-info/entry_points.txt
craigslist_rental_market-0.1.0.dist-info/metadata.json
craigslist_rental_market-0.1.0.dist-info/top_level.txt
