Metadata-Version: 2.0
Name: craigslist-rental-market
Version: 0.1.0
Summary: Display Craigslist rental market statistics
Home-page: https://github.com/brbsix/craigslist-rental-market
Author: Brian Beffa
Author-email: brbsix@gmail.com
License: GPLv3
Keywords: craigslist,scraper,scraping
Platform: UNKNOWN
Classifier: Development Status :: 4 - Beta
Classifier: Environment :: Console
Classifier: Intended Audience :: Developers
Classifier: Intended Audience :: End Users/Desktop
Classifier: License :: OSI Approved :: GNU General Public License v3 (GPLv3)
Classifier: Natural Language :: English
Classifier: Operating System :: POSIX
Classifier: Operating System :: POSIX :: Linux
Classifier: Programming Language :: Python :: 3
Classifier: Programming Language :: Python :: 3.0
Classifier: Programming Language :: Python :: 3.1
Classifier: Programming Language :: Python :: 3.2
Classifier: Programming Language :: Python :: 3.3
Classifier: Programming Language :: Python :: 3.4
Classifier: Programming Language :: Python :: 3 :: Only
Classifier: Topic :: Utilities
Requires-Dist: appdirs
Requires-Dist: beautifulsoup4
Requires-Dist: inquirer
Requires-Dist: requests
Requires-Dist: requests-cache (>=0.4.11)
